[
  {
    "movie": "Border 2",
    "venue": "Chhotu Maharaj Cine Cafe: Charkhi Dadri",
    "address": "Main Loharu Road, Rose Petals Hotel Restaurant, Charkhi Dadri, Haryana 127306, India",
    "language": "Hindi",
    "dimension": "2D",
    "chain": "K Sera Sera Box Office Pvt. Ltd.",
    "time": "08:00 AM",
    "audi": "",
    "session_id": "1611",
    "totalSeats": 100,
    "available": 100,
    "sold": 0,
    "gross": 0,
    "city": "Charkhi Dadri",
    "state": "Haryana",
    "source": "BMS",
    "date": "20260215",
    "minutes_left": 142.0
  },
  {
    "movie": "Border 2",
    "venue": "MovieMax: Eternity, Nagpur",
    "address": "MovieMax, 4th Floor, Variety Square, Sitabuldi, Nagpur, Maharashtra 440012, India",
    "language": "Hindi",
    "dimension": "2D",
    "chain": "MovieMax",
    "time": "08:30 AM",
    "audi": "DOLBY 7.1",
    "session_id": "29654",
    "totalSeats": 257,
    "available": 145,
    "sold": 112,
    "gross": 20510,
    "city": "Nagpur",
    "state": "Maharashtra",
    "source": "BMS",
    "date": "20260215",
    "minutes_left": 172.0
  },
  {
    "movie": "O' Romeo",
    "venue": "City Pride: Kothrud",
    "address": "Survey No.20/1,2, Kothrud, Near Tara Residency, Pune, Maharashtra 411038, India",
    "language": "Hindi",
    "dimension": "2D",
    "chain": "City Pride",
    "time": "08:30 AM",
    "audi": "4K DOLBY",
    "session_id": "122329",
    "totalSeats": 504,
    "available": 448,
    "sold": 56,
    "gross": 10080,
    "city": "Pune",
    "state": "Maharashtra",
    "source": "BMS",
    "date": "20260215",
    "minutes_left": 172.0
  },
  {
    "movie": "O' Romeo",
    "venue": "INOX: Elpro City Square, Chinchwad",
    "address": "2nd Floor, Elpro City Square Mall, Pimpri Chinchwad Link Road, Pune, Maharashtra 411033, India",
    "language": "Hindi",
    "dimension": "2D",
    "chain": "INOX",
    "time": "08:00 AM",
    "audi": "",
    "session_id": "52945",
    "totalSeats": 265,
    "available": 247,
    "sold": 18,
    "gross": 4930,
    "city": "Pune",
    "state": "Maharashtra",
    "source": "BMS",
    "date": "20260215",
    "minutes_left": 142.0
  },
  {
    "movie": "O' Romeo",
    "venue": "Abhiruchi City Pride: Sinhagad Road",
    "address": "Near Flyover, Sinhagad Road, Vadgaon Budruk, Pune, Maharashtra 411041, India",
    "language": "Hindi",
    "dimension": "2D",
    "chain": "City Pride",
    "time": "08:30 AM",
    "audi": "DOLBY 7.1",
    "session_id": "135708",
    "totalSeats": 315,
    "available": 281,
    "sold": 34,
    "gross": 6320,
    "city": "Pune",
    "state": "Maharashtra",
    "source": "BMS",
    "date": "20260215",
    "minutes_left": 172.0
  },
  {
    "movie": "O' Romeo",
    "venue": "Rahul 70 MM: Shivajinagar, Pune",
    "address": "Ganeshkhind Road, Shivaji Nagar, Narveer Tanaji Wadi, Pune, Maharashtra 411004, India",
    "language": "Hindi",
    "dimension": "2D",
    "chain": "Rahul Cineplex: Pune",
    "time": "08:30 AM",
    "audi": "",
    "session_id": "9979",
    "totalSeats": 542,
    "available": 502,
    "sold": 40,
    "gross": 4000,
    "city": "Pune",
    "state": "Maharashtra",
    "source": "BMS",
    "date": "20260215",
    "minutes_left": 172.0
  }
]