{
  "Wuthering Heights": {
    "shows": 1,
    "gross": 0.0,
    "sold": 0,
    "totalSeats": 163,
    "venues": 1,
    "cities": 1,
    "fastfilling": 0,
    "housefull": 0,
    "occupancy": 0.0,
    "City_details": [
      {
        "city": "Ahmedabad",
        "state": "Gujarat",
        "venues": 1,
        "shows": 1,
        "gross": 0.0,
        "sold": 0,
        "totalSeats": 163,
        "fastfilling": 0,
        "housefull": 0,
        "occupancy": 0.0
      }
    ],
    "Language_details": [
      {
        "language": "English",
        "venues": 1,
        "shows": 1,
        "gross": 0.0,
        "sold": 0,
        "totalSeats": 163,
        "fastfilling": 0,
        "housefull": 0,
        "occupancy": 0.0
      }
    ],
    "Format_details": [
      {
        "dimension": "2D",
        "venues": 1,
        "shows": 1,
        "gross": 0.0,
        "sold": 0,
        "totalSeats": 163,
        "fastfilling": 0,
        "housefull": 0,
        "occupancy": 0.0
      }
    ]
  },
  "O' Romeo": {
    "shows": 8,
    "gross": 1920.0,
    "sold": 9,
    "totalSeats": 404,
    "venues": 7,
    "cities": 1,
    "fastfilling": 0,
    "housefull": 0,
    "occupancy": 2.23,
    "City_details": [
      {
        "city": "Ahmedabad",
        "state": "Gujarat",
        "venues": 7,
        "shows": 8,
        "gross": 1920.0,
        "sold": 9,
        "totalSeats": 404,
        "fastfilling": 0,
        "housefull": 0,
        "occupancy": 2.23
      }
    ],
    "Language_details": [
      {
        "language": "Hindi",
        "venues": 7,
        "shows": 8,
        "gross": 1920.0,
        "sold": 9,
        "totalSeats": 404,
        "fastfilling": 0,
        "housefull": 0,
        "occupancy": 2.23
      }
    ],
    "Format_details": [
      {
        "dimension": "2D",
        "venues": 7,
        "shows": 8,
        "gross": 1920.0,
        "sold": 9,
        "totalSeats": 404,
        "fastfilling": 0,
        "housefull": 0,
        "occupancy": 2.23
      }
    ]
  },
  "Border 2": {
    "shows": 1,
    "gross": 0.0,
    "sold": 0,
    "totalSeats": 50,
    "venues": 1,
    "cities": 1,
    "fastfilling": 0,
    "housefull": 0,
    "occupancy": 0.0,
    "City_details": [
      {
        "city": "Ahmedabad",
        "state": "Gujarat",
        "venues": 1,
        "shows": 1,
        "gross": 0.0,
        "sold": 0,
        "totalSeats": 50,
        "fastfilling": 0,
        "housefull": 0,
        "occupancy": 0.0
      }
    ],
    "Language_details": [
      {
        "language": "Hindi",
        "venues": 1,
        "shows": 1,
        "gross": 0.0,
        "sold": 0,
        "totalSeats": 50,
        "fastfilling": 0,
        "housefull": 0,
        "occupancy": 0.0
      }
    ],
    "Format_details": [
      {
        "dimension": "2D",
        "venues": 1,
        "shows": 1,
        "gross": 0.0,
        "sold": 0,
        "totalSeats": 50,
        "fastfilling": 0,
        "housefull": 0,
        "occupancy": 0.0
      }
    ]
  },
  "Lagan Laagii Re": {
    "shows": 1,
    "gross": 0.0,
    "sold": 0,
    "totalSeats": 63,
    "venues": 1,
    "cities": 1,
    "fastfilling": 0,
    "housefull": 0,
    "occupancy": 0.0,
    "City_details": [
      {
        "city": "Ahmedabad",
        "state": "Gujarat",
        "venues": 1,
        "shows": 1,
        "gross": 0.0,
        "sold": 0,
        "totalSeats": 63,
        "fastfilling": 0,
        "housefull": 0,
        "occupancy": 0.0
      }
    ],
    "Language_details": [
      {
        "language": "Gujarati",
        "venues": 1,
        "shows": 1,
        "gross": 0.0,
        "sold": 0,
        "totalSeats": 63,
        "fastfilling": 0,
        "housefull": 0,
        "occupancy": 0.0
      }
    ],
    "Format_details": [
      {
        "dimension": "2D",
        "venues": 1,
        "shows": 1,
        "gross": 0.0,
        "sold": 0,
        "totalSeats": 63,
        "fastfilling": 0,
        "housefull": 0,
        "occupancy": 0.0
      }
    ]
  },
  "Tu Meri Main Tera Main Tera Tu Meri": {
    "shows": 2,
    "gross": 0.0,
    "sold": 0,
    "totalSeats": 48,
    "venues": 2,
    "cities": 1,
    "fastfilling": 0,
    "housefull": 0,
    "occupancy": 0.0,
    "City_details": [
      {
        "city": "Ahmedabad",
        "state": "Gujarat",
        "venues": 2,
        "shows": 2,
        "gross": 0.0,
        "sold": 0,
        "totalSeats": 48,
        "fastfilling": 0,
        "housefull": 0,
        "occupancy": 0.0
      }
    ],
    "Language_details": [
      {
        "language": "Hindi",
        "venues": 2,
        "shows": 2,
        "gross": 0.0,
        "sold": 0,
        "totalSeats": 48,
        "fastfilling": 0,
        "housefull": 0,
        "occupancy": 0.0
      }
    ],
    "Format_details": [
      {
        "dimension": "2D",
        "venues": 2,
        "shows": 2,
        "gross": 0.0,
        "sold": 0,
        "totalSeats": 48,
        "fastfilling": 0,
        "housefull": 0,
        "occupancy": 0.0
      }
    ]
  },
  "Mardaani 3": {
    "shows": 2,
    "gross": 0.0,
    "sold": 0,
    "totalSeats": 31,
    "venues": 2,
    "cities": 1,
    "fastfilling": 0,
    "housefull": 0,
    "occupancy": 0.0,
    "City_details": [
      {
        "city": "Ahmedabad",
        "state": "Gujarat",
        "venues": 2,
        "shows": 2,
        "gross": 0.0,
        "sold": 0,
        "totalSeats": 31,
        "fastfilling": 0,
        "housefull": 0,
        "occupancy": 0.0
      }
    ],
    "Language_details": [
      {
        "language": "Hindi",
        "venues": 2,
        "shows": 2,
        "gross": 0.0,
        "sold": 0,
        "totalSeats": 31,
        "fastfilling": 0,
        "housefull": 0,
        "occupancy": 0.0
      }
    ],
    "Format_details": [
      {
        "dimension": "2D",
        "venues": 2,
        "shows": 2,
        "gross": 0.0,
        "sold": 0,
        "totalSeats": 31,
        "fastfilling": 0,
        "housefull": 0,
        "occupancy": 0.0
      }
    ]
  }
}